<?xml version="1.0" encoding="utf-8" ?>
<chartdatalist>
<chartdataisland>
<chartdata>
<x legend='Excel Printable DVD-R 4.7G 16X'>0</x>
<y>9.72</y>
</chartdata>
<chartdata>
<x legend='Network Cable Plug'>1</x>
<y>9.36</y>
</chartdata>
<chartdata>
<x legend='Network Cable'>2</x>
<y>8.148</y>
</chartdata>
<chartdata>
<x legend='Power Cord Extension 5M'>3</x>
<y>1.15</y>
</chartdata>
<chartdata>
<x legend='Logitech Deluxe 250 Desktop Keyboard   Optical Mouse - Black'>4</x>
<y>31.1</y>
</chartdata>
<chartdata>
<x legend='LABOUR FEE'>5</x>
<y>149.444</y>
</chartdata>
<chartdata>
<x legend='VGA Monitor Cable 5m'>6</x>
<y>20.94</y>
</chartdata>
<chartdata>
<x legend='Asus 802.11b/g Pen-type USB'>7</x>
<y>32.92</y>
</chartdata>
<chartdata>
<x legend='Powerboard 4 Outlet Slimline'>8</x>
<y>1.22</y>
</chartdata>
<chartdata>
<x legend='Hynix 1G DDR400'>9</x>
<y>44.08</y>
</chartdata>
<chartdata>
<x legend='USB 2.0 Extension A-A M-F Cable 2m'>10</x>
<y>13.18</y>
</chartdata>
<chartdata>
<x legend='Transcend 2GB JetFlash V30 USB 2.0 - Red'>11</x>
<y>-11.08</y>
</chartdata>
<chartdata>
<x legend='Kingmax 1Gb DDR2-800'>12</x>
<y>13.97</y>
</chartdata>
<chartdata>
<x legend='Kingmax 8GB USB2.0 Flash Drive --- Blue'>13</x>
<y>14.53</y>
</chartdata>
<chartdata>
<x legend='Asus 8400GS 256MB PCIE'>14</x>
<y>16.72</y>
</chartdata>
<chartdata>
<x legend='USB 2.0 EXT CABLE - 2M'>15</x>
<y>6.59</y>
</chartdata>
<chartdata>
<x legend='Samsung 22" 226BW widescreen LCD monitor 2ms response'>16</x>
<y>38.9</y>
</chartdata>
<chartdata>
<x legend='Hyena 350W ball bearing ATX Power Supply, SATA connector,Intel approved Latest version 2.2'>17</x>
<y>16.53</y>
</chartdata>
<chartdata>
<x legend='Task TK945TX 450W PSU'>18</x>
<y>19.27</y>
</chartdata>
<chartdata>
<x legend='Transcend 2.5" IDE StoreJet HD External Enclosure USB 2.0 Interface (Silver)'>19</x>
<y>4.1</y>
</chartdata>
<chartdata>
<x legend='Transcend 2.5" S HDD Ext Box'>20</x>
<y>11.21</y>
</chartdata>
<chartdata>
<x legend='Transcend 2.5" StoreJet HD External Enclosure USB 2.0 Interface (Red)'>21</x>
<y>13.26</y>
</chartdata>
<chartdata>
<x legend='WD 2.5" 120GB 5400RPM 8MB IDE'>22</x>
<y>24.75</y>
</chartdata>
<chartdata>
<x legend='Western Digital Scorpio 2.5 inch 120GB EIDE 5400RPM 8MB Cache'>23</x>
<y>13.64</y>
</chartdata>
<chartdata>
<x legend='Seagate FreeAgent Desktop 320G External Hard Drive'>24</x>
<y>18.86</y>
</chartdata>
<chartdata>
<x legend='Western Digital Scorpio 2.5 inch 250GB EIDE 5400RPM 8MB Cache'>25</x>
<y>15</y>
</chartdata>
<chartdata>
<x legend='Navigator Luxury 2.5" IDE EXT. Enclosure'>26</x>
<y>18.328</y>
</chartdata>
<chartdata>
<x legend='VGA Monitor Cable HD15M-HD15M with Filter UL Approved 10m'>27</x>
<y>10.9</y>
</chartdata>
<chartdata>
<x legend='VGA Monitor Cable HD15M-HD15M with Filter UL Approved 20m'>28</x>
<y>16.45</y>
</chartdata>
<chartdata>
<x legend='Power Double Adaptor'>29</x>
<y>0</y>
</chartdata>
<chartdata>
<x legend='Asus WL520GC Wireless Router'>30</x>
<y>38.12</y>
</chartdata>
<chartdata>
<x legend='Asus WL520GC Wireless Router 125Mbps With EZSetup No Modem'>31</x>
<y>38.124</y>
</chartdata>
<chartdata>
<x legend='Logitech Media Keyboard 600'>32</x>
<y>15.7</y>
</chartdata>
<chartdata>
<x legend='A4Tech OP-50B 3D Optical Mouse'>33</x>
<y>9.96</y>
</chartdata>
<chartdata>
<x legend='Logitech V470 Bluetooth Laser Mouse - Blue'>34</x>
<y>35.83</y>
</chartdata>
<chartdata>
<x legend='GIGABYTE Poseidon MidTower ATX Chassis no power supply'>35</x>
<y>49</y>
</chartdata>
<chartdata>
<x legend='TK-6110 Crystal White w/ PSU'>36</x>
<y>30</y>
</chartdata>
</chartdataisland>
<chartdataisland>
<chartdata>
<x legend='Excel Printable DVD-R 4.7G 16X'>0</x>
<y>14.28</y>
</chartdata>
<chartdata>
<x legend='Network Cable Plug'>1</x>
<y>8.4</y>
</chartdata>
<chartdata>
<x legend='Network Cable'>2</x>
<y>2.52</y>
</chartdata>
<chartdata>
<x legend='Power Cord Extension 5M'>3</x>
<y>27.35</y>
</chartdata>
<chartdata>
<x legend='Logitech Deluxe 250 Desktop Keyboard   Optical Mouse - Black'>4</x>
<y>80</y>
</chartdata>
<chartdata>
<x legend='LABOUR FEE'>5</x>
<y>0</y>
</chartdata>
<chartdata>
<x legend='VGA Monitor Cable 5m'>6</x>
<y>32.4</y>
</chartdata>
<chartdata>
<x legend='Asus 802.11b/g Pen-type USB'>7</x>
<y>47.08</y>
</chartdata>
<chartdata>
<x legend='Powerboard 4 Outlet Slimline'>8</x>
<y>4.44</y>
</chartdata>
<chartdata>
<x legend='Hynix 1G DDR400'>9</x>
<y>108.8</y>
</chartdata>
<chartdata>
<x legend='USB 2.0 Extension A-A M-F Cable 2m'>10</x>
<y>2.82</y>
</chartdata>
<chartdata>
<x legend='Transcend 2GB JetFlash V30 USB 2.0 - Red'>11</x>
<y>43.08</y>
</chartdata>
<chartdata>
<x legend='Kingmax 1Gb DDR2-800'>12</x>
<y>26.03</y>
</chartdata>
<chartdata>
<x legend='Kingmax 8GB USB2.0 Flash Drive --- Blue'>13</x>
<y>44.47</y>
</chartdata>
<chartdata>
<x legend='Asus 8400GS 256MB PCIE'>14</x>
<y>63.28</y>
</chartdata>
<chartdata>
<x legend='USB 2.0 EXT CABLE - 2M'>15</x>
<y>1.41</y>
</chartdata>
<chartdata>
<x legend='Samsung 22" 226BW widescreen LCD monitor 2ms response'>16</x>
<y>400.1</y>
</chartdata>
<chartdata>
<x legend='Hyena 350W ball bearing ATX Power Supply, SATA connector,Intel approved Latest version 2.2'>17</x>
<y>27.91</y>
</chartdata>
<chartdata>
<x legend='Task TK945TX 450W PSU'>18</x>
<y>39.73</y>
</chartdata>
<chartdata>
<x legend='Transcend 2.5" IDE StoreJet HD External Enclosure USB 2.0 Interface (Silver)'>19</x>
<y>22.57</y>
</chartdata>
<chartdata>
<x legend='Transcend 2.5" S HDD Ext Box'>20</x>
<y>22.57</y>
</chartdata>
<chartdata>
<x legend='Transcend 2.5" StoreJet HD External Enclosure USB 2.0 Interface (Red)'>21</x>
<y>24.52</y>
</chartdata>
<chartdata>
<x legend='WD 2.5" 120GB 5400RPM 8MB IDE'>22</x>
<y>86.36</y>
</chartdata>
<chartdata>
<x legend='Western Digital Scorpio 2.5 inch 120GB EIDE 5400RPM 8MB Cache'>23</x>
<y>86.36</y>
</chartdata>
<chartdata>
<x legend='Seagate FreeAgent Desktop 320G External Hard Drive'>24</x>
<y>140.25</y>
</chartdata>
<chartdata>
<x legend='Western Digital Scorpio 2.5 inch 250GB EIDE 5400RPM 8MB Cache'>25</x>
<y>145</y>
</chartdata>
<chartdata>
<x legend='Navigator Luxury 2.5" IDE EXT. Enclosure'>26</x>
<y>15.45</y>
</chartdata>
<chartdata>
<x legend='VGA Monitor Cable HD15M-HD15M with Filter UL Approved 10m'>27</x>
<y>18.1</y>
</chartdata>
<chartdata>
<x legend='VGA Monitor Cable HD15M-HD15M with Filter UL Approved 20m'>28</x>
<y>32.55</y>
</chartdata>
<chartdata>
<x legend='Power Double Adaptor'>29</x>
<y>1.76</y>
</chartdata>
<chartdata>
<x legend='Asus WL520GC Wireless Router'>30</x>
<y>40.88</y>
</chartdata>
<chartdata>
<x legend='Asus WL520GC Wireless Router 125Mbps With EZSetup No Modem'>31</x>
<y>40.88</y>
</chartdata>
<chartdata>
<x legend='Logitech Media Keyboard 600'>32</x>
<y>29.3</y>
</chartdata>
<chartdata>
<x legend='A4Tech OP-50B 3D Optical Mouse'>33</x>
<y>9.04</y>
</chartdata>
<chartdata>
<x legend='Logitech V470 Bluetooth Laser Mouse - Blue'>34</x>
<y>53.17</y>
</chartdata>
<chartdata>
<x legend='GIGABYTE Poseidon MidTower ATX Chassis no power supply'>35</x>
<y>110</y>
</chartdata>
<chartdata>
<x legend='TK-6110 Crystal White w/ PSU'>36</x>
<y>40</y>
</chartdata>
</chartdataisland>
<chartdataisland>
<chartdata>
<x legend='Excel Printable DVD-R 4.7G 16X'>0</x>
<y>24</y>
</chartdata>
<chartdata>
<x legend='Network Cable Plug'>1</x>
<y>17.76</y>
</chartdata>
<chartdata>
<x legend='Network Cable'>2</x>
<y>10.668</y>
</chartdata>
<chartdata>
<x legend='Power Cord Extension 5M'>3</x>
<y>28.5</y>
</chartdata>
<chartdata>
<x legend='Logitech Deluxe 250 Desktop Keyboard   Optical Mouse - Black'>4</x>
<y>111.1</y>
</chartdata>
<chartdata>
<x legend='LABOUR FEE'>5</x>
<y>149.444</y>
</chartdata>
<chartdata>
<x legend='VGA Monitor Cable 5m'>6</x>
<y>53.34</y>
</chartdata>
<chartdata>
<x legend='Asus 802.11b/g Pen-type USB'>7</x>
<y>80</y>
</chartdata>
<chartdata>
<x legend='Powerboard 4 Outlet Slimline'>8</x>
<y>5.66</y>
</chartdata>
<chartdata>
<x legend='Hynix 1G DDR400'>9</x>
<y>152.88</y>
</chartdata>
<chartdata>
<x legend='USB 2.0 Extension A-A M-F Cable 2m'>10</x>
<y>16</y>
</chartdata>
<chartdata>
<x legend='Transcend 2GB JetFlash V30 USB 2.0 - Red'>11</x>
<y>32</y>
</chartdata>
<chartdata>
<x legend='Kingmax 1Gb DDR2-800'>12</x>
<y>40</y>
</chartdata>
<chartdata>
<x legend='Kingmax 8GB USB2.0 Flash Drive --- Blue'>13</x>
<y>59</y>
</chartdata>
<chartdata>
<x legend='Asus 8400GS 256MB PCIE'>14</x>
<y>80</y>
</chartdata>
<chartdata>
<x legend='USB 2.0 EXT CABLE - 2M'>15</x>
<y>8</y>
</chartdata>
<chartdata>
<x legend='Samsung 22" 226BW widescreen LCD monitor 2ms response'>16</x>
<y>439</y>
</chartdata>
<chartdata>
<x legend='Hyena 350W ball bearing ATX Power Supply, SATA connector,Intel approved Latest version 2.2'>17</x>
<y>44.44</y>
</chartdata>
<chartdata>
<x legend='Task TK945TX 450W PSU'>18</x>
<y>59</y>
</chartdata>
<chartdata>
<x legend='Transcend 2.5" IDE StoreJet HD External Enclosure USB 2.0 Interface (Silver)'>19</x>
<y>26.67</y>
</chartdata>
<chartdata>
<x legend='Transcend 2.5" S HDD Ext Box'>20</x>
<y>33.78</y>
</chartdata>
<chartdata>
<x legend='Transcend 2.5" StoreJet HD External Enclosure USB 2.0 Interface (Red)'>21</x>
<y>37.78</y>
</chartdata>
<chartdata>
<x legend='WD 2.5" 120GB 5400RPM 8MB IDE'>22</x>
<y>111.11</y>
</chartdata>
<chartdata>
<x legend='Western Digital Scorpio 2.5 inch 120GB EIDE 5400RPM 8MB Cache'>23</x>
<y>100</y>
</chartdata>
<chartdata>
<x legend='Seagate FreeAgent Desktop 320G External Hard Drive'>24</x>
<y>159.11</y>
</chartdata>
<chartdata>
<x legend='Western Digital Scorpio 2.5 inch 250GB EIDE 5400RPM 8MB Cache'>25</x>
<y>160</y>
</chartdata>
<chartdata>
<x legend='Navigator Luxury 2.5" IDE EXT. Enclosure'>26</x>
<y>33.778</y>
</chartdata>
<chartdata>
<x legend='VGA Monitor Cable HD15M-HD15M with Filter UL Approved 10m'>27</x>
<y>29</y>
</chartdata>
<chartdata>
<x legend='VGA Monitor Cable HD15M-HD15M with Filter UL Approved 20m'>28</x>
<y>49</y>
</chartdata>
<chartdata>
<x legend='Power Double Adaptor'>29</x>
<y>1.76</y>
</chartdata>
<chartdata>
<x legend='Asus WL520GC Wireless Router'>30</x>
<y>79</y>
</chartdata>
<chartdata>
<x legend='Asus WL520GC Wireless Router 125Mbps With EZSetup No Modem'>31</x>
<y>79.004</y>
</chartdata>
<chartdata>
<x legend='Logitech Media Keyboard 600'>32</x>
<y>45</y>
</chartdata>
<chartdata>
<x legend='A4Tech OP-50B 3D Optical Mouse'>33</x>
<y>19</y>
</chartdata>
<chartdata>
<x legend='Logitech V470 Bluetooth Laser Mouse - Blue'>34</x>
<y>89</y>
</chartdata>
<chartdata>
<x legend='GIGABYTE Poseidon MidTower ATX Chassis no power supply'>35</x>
<y>159</y>
</chartdata>
<chartdata>
<x legend='TK-6110 Crystal White w/ PSU'>36</x>
<y>70</y>
</chartdata>
</chartdataisland>
</chartdatalist>
